opml_translate/__init__.py
opml_translate/command_line.py
opml_translate/translate.py
opml_translate-0.1.2.dist-info/LICENSE
opml_translate-0.1.2.dist-info/METADATA
opml_translate-0.1.2.dist-info/WHEEL
opml_translate-0.1.2.dist-info/entry_points.txt
opml_translate-0.1.2.dist-info/top_level.txt
opml_translate-0.1.2.dist-info/RECORD
