Metadata-Version: 2.1
Name: opml-translate
Version: 0.1.2
Summary: Translates OPML files
Home-page: https://github.com/DanielPechersky/opml-translate
Author: Daniel Pechersky
Author-email: danny.pechersky@gmail.com
License: UNKNOWN
Platform: UNKNOWN
Classifier: Development Status :: 3 - Alpha
Classifier: License :: OSI Approved :: MIT License
Classifier: Programming Language :: Python :: 3
Classifier: Programming Language :: Python :: 3.7
Requires-Dist: translate
Requires-Dist: click
Requires-Dist: click-log
